[
    {
        "pk": 248180034,
        "username": "tsai_ingwen",
        "full_name": "\u8521\u82f1\u6587",
        "is_private": false,
        "profile_pic_url": "https://scontent-sea1-1.cdninstagram.com/v/t51.2885-19/264951609_733177598085086_8360335928358204547_n.jpg?stp=dst-jpg_s150x150&_nc_ht=scontent-sea1-1.cdninstagram.com&_nc_cat=1&_nc_ohc=knr5Sk_JEyUAX-B0aiD&edm=ALB854YBAAAA&ccb=7-4&oh=00_AT_YYZ8HnCbVx8uENb8ww6j0eXKH-Yyt36nYqhyWELEQEQ&oe=6246B2F3&_nc_sid=04cb80",
        "profile_pic_id": "2723990073623561438_248180034",
        "is_verified": true,
        "follow_friction_type": 0,
        "growth_friction_info": {
            "has_active_interventions": false,
            "interventions": {}
        },
        "account_badges": [],
        "has_anonymous_profile_picture": false,
        "has_highlight_reels": false,
        "has_primary_country_in_feed": false,
        "has_primary_country_in_profile": false,
        "latest_reel_media": 0,
        "is_favorite": false
    },
    {
        "pk": 7472572184,
        "username": "chiayionefish",
        "full_name": "\u8521\u6613\u9918",
        "is_private": false,
        "profile_pic_url": "https://scontent-sea1-1.cdninstagram.com/v/t51.2885-19/146350147_3739941129425752_5763501349752314032_n.jpg?stp=dst-jpg_s150x150&_nc_ht=scontent-sea1-1.cdninstagram.com&_nc_cat=104&_nc_ohc=s2MBShrMFucAX9OzEJ1&edm=ALB854YBAAAA&ccb=7-4&oh=00_AT_Nj7tc179kf1f8SRBzPcj_QPqhCrE3ymMhWGkdS4UxKg&oe=6247C438&_nc_sid=04cb80",
        "profile_pic_id": "2503081678210342602_7472572184",
        "is_verified": false,
        "follow_friction_type": 0,
        "growth_friction_info": {
            "has_active_interventions": false,
            "interventions": {}
        },
        "account_badges": [],
        "has_anonymous_profile_picture": false,
        "has_highlight_reels": false,
        "has_primary_country_in_feed": false,
        "has_primary_country_in_profile": false,
        "latest_reel_media": 0,
        "is_favorite": false
    },
    {
        "pk": 1693185827,
        "username": "daniela_kluckert",
        "full_name": "Daniela Kluckert",
        "is_private": false,
        "profile_pic_url": "https://scontent-sea1-1.cdninstagram.com/v/t51.2885-19/127529434_882936555849814_2178750288703833017_n.jpg?stp=dst-jpg_s150x150&_nc_ht=scontent-sea1-1.cdninstagram.com&_nc_cat=110&_nc_ohc=ErKkWmOv1SEAX_27l-o&edm=ALB854YBAAAA&ccb=7-4&oh=00_AT9XuW1io4ogOK0jUokkrxXkHWFnG0qVwm8Na69Pt_h9cw&oe=6247AF93&_nc_sid=04cb80",
        "profile_pic_id": "2449419187217586381_1693185827",
        "is_verified": true,
        "follow_friction_type": 0,
        "growth_friction_info": {
            "has_active_interventions": false,
            "interventions": {}
        },
        "account_badges": [],
        "has_anonymous_profile_picture": false,
        "has_highlight_reels": false,
        "has_primary_country_in_feed": false,
        "has_primary_country_in_profile": false,
        "latest_reel_media": 0,
        "is_favorite": false
    },
    {
        "pk": 8544006,
        "username": "su.chiaohui",
        "full_name": "\u8607\u5de7\u6167",
        "is_private": false,
        "profile_pic_url": "https://scontent-sea1-1.cdninstagram.com/v/t51.2885-19/116134388_586831118669706_1981848333814187577_n.jpg?stp=dst-jpg_s150x150&_nc_ht=scontent-sea1-1.cdninstagram.com&_nc_cat=106&_nc_ohc=sNoHls1-m44AX99Ao2C&tn=5_nM7iDSx2Jrx7n9&edm=ALB854YBAAAA&ccb=7-4&oh=00_AT8U9MfMD8Gceezoo11AbDHwBgbDFk7Z9Dlq83P_RRbPMA&oe=62474570&_nc_sid=04cb80",
        "profile_pic_id": "2362325124354397160_8544006",
        "is_verified": true,
        "follow_friction_type": 0,
        "growth_friction_info": {
            "has_active_interventions": false,
            "interventions": {}
        },
        "account_badges": [],
        "has_anonymous_profile_picture": false,
        "has_highlight_reels": false,
        "has_primary_country_in_feed": false,
        "has_primary_country_in_profile": false,
        "latest_reel_media": 1648299012,
        "is_favorite": false
    },
    {
        "pk": 11770100145,
        "username": "oakmega",
        "full_name": "OakMega \u5927\u6a61\u79d1\u6280",
        "is_private": false,
        "profile_pic_url": "https://scontent-sea1-1.cdninstagram.com/v/t51.2885-19/271134950_332147722092605_1939684644220153719_n.jpg?stp=dst-jpg_s150x150&_nc_ht=scontent-sea1-1.cdninstagram.com&_nc_cat=105&_nc_ohc=205NQxspOc4AX-1I6p2&edm=ALB854YBAAAA&ccb=7-4&oh=00_AT_5-wS-oKd-FfrjmfIlF_zTWJE-uJn_PYkhByzQun_dww&oe=62474937&_nc_sid=04cb80",
        "profile_pic_id": "2742766688312596641_11770100145",
        "is_verified": false,
        "follow_friction_type": 0,
        "growth_friction_info": {
            "has_active_interventions": false,
            "interventions": {}
        },
        "account_badges": [],
        "has_anonymous_profile_picture": false,
        "has_highlight_reels": false,
        "has_primary_country_in_feed": false,
        "has_primary_country_in_profile": false,
        "latest_reel_media": 0,
        "is_favorite": false
    },
    {
        "pk": 3906188934,
        "username": "herbsttorsten",
        "full_name": "Torsten Herbst",
        "is_private": false,
        "profile_pic_url": "https://scontent-sea1-1.cdninstagram.com/v/t51.2885-19/33145355_607192059643588_6976154274669527040_n.jpg?stp=dst-jpg_s150x150&_nc_ht=scontent-sea1-1.cdninstagram.com&_nc_cat=104&_nc_ohc=IUcZLnVWtAsAX_l6iMu&edm=ALB854YBAAAA&ccb=7-4&oh=00_AT9emN1nMKqyHDMDEFhZ1rZqt1rfO9r2AoIEFMuggzsEhw&oe=6246ED65&_nc_sid=04cb80",
        "profile_pic_id": "1794318635026403155_3906188934",
        "is_verified": true,
        "follow_friction_type": 0,
        "growth_friction_info": {
            "has_active_interventions": false,
            "interventions": {}
        },
        "account_badges": [],
        "has_anonymous_profile_picture": false,
        "has_highlight_reels": false,
        "has_primary_country_in_feed": false,
        "has_primary_country_in_profile": false,
        "latest_reel_media": 0,
        "is_favorite": false
    },
    {
        "pk": 1459510110,
        "username": "aray_comix",
        "full_name": "A RAY",
        "is_private": false,
        "profile_pic_url": "https://scontent-sea1-1.cdninstagram.com/v/t51.2885-19/172939905_913089489448953_4178361206706117276_n.jpg?stp=dst-jpg_s150x150&_nc_ht=scontent-sea1-1.cdninstagram.com&_nc_cat=109&_nc_ohc=Lj9zVvQckMwAX_0tTrL&edm=ALB854YBAAAA&ccb=7-4&oh=00_AT-OLHk5W225usczDeMcDGj6H7rkC4E2ck-aZWumiWirhA&oe=6246C5C1&_nc_sid=04cb80",
        "profile_pic_id": "2552479469474727237_1459510110",
        "is_verified": true,
        "follow_friction_type": 0,
        "growth_friction_info": {
            "has_active_interventions": false,
            "interventions": {}
        },
        "account_badges": [],
        "has_anonymous_profile_picture": false,
        "has_highlight_reels": false,
        "has_primary_country_in_feed": false,
        "has_primary_country_in_profile": false,
        "latest_reel_media": 1648369024,
        "is_favorite": false
    },
    {
        "pk": 8657556186,
        "username": "iloventur",
        "full_name": "\u9673\u9999\u83ca(\u65b0\u5317\u57ce\u9109\u5c40)",
        "is_private": false,
        "profile_pic_url": "https://scontent-sea1-1.cdninstagram.com/v/t51.2885-19/273627490_488575436180762_1978321144818559413_n.jpg?stp=dst-jpg_s150x150&_nc_ht=scontent-sea1-1.cdninstagram.com&_nc_cat=102&_nc_ohc=-7EdhEtSH0YAX9zPjLt&edm=ALB854YBAAAA&ccb=7-4&oh=00_AT_JpjoDEO5gFsA6HTmWJd7JYhn70LmnpeYbFNJo-QUwmA&oe=6246FE72&_nc_sid=04cb80",
        "profile_pic_id": "2770477346502146563_8657556186",
        "is_verified": false,
        "follow_friction_type": 0,
        "growth_friction_info": {
            "has_active_interventions": false,
            "interventions": {}
        },
        "account_badges": [],
        "has_anonymous_profile_picture": false,
        "has_highlight_reels": false,
        "has_primary_country_in_feed": false,
        "has_primary_country_in_profile": false,
        "latest_reel_media": 0,
        "is_favorite": false
    },
    {
        "pk": 9502122423,
        "username": "cafe_pingtung",
        "full_name": "\u937e\u4f73\u6ff1",
        "is_private": false,
        "profile_pic_url": "https://scontent-sea1-1.cdninstagram.com/v/t51.2885-19/117717911_314761616538297_7956067856022939592_n.jpg?stp=dst-jpg_s150x150&_nc_ht=scontent-sea1-1.cdninstagram.com&_nc_cat=109&_nc_ohc=valK0enLGlUAX9bkJIx&tn=5_nM7iDSx2Jrx7n9&edm=ALB854YBAAAA&ccb=7-4&oh=00_AT92fu2InCRbNvY8YP6mJdyqdgLhcPWqiOtINL4FJdprYA&oe=62469727&_nc_sid=04cb80",
        "profile_pic_id": "2377710058447145866_9502122423",
        "is_verified": true,
        "follow_friction_type": 0,
        "growth_friction_info": {
            "has_active_interventions": false,
            "interventions": {}
        },
        "account_badges": [],
        "has_anonymous_profile_picture": false,
        "has_highlight_reels": false,
        "has_primary_country_in_feed": false,
        "has_primary_country_in_profile": false,
        "latest_reel_media": 1648381626,
        "is_favorite": false
    },
    {
        "pk": 12827775107,
        "username": "wajinpie",
        "full_name": "\u8fa3\u53f0\u6d3e",
        "is_private": false,
        "profile_pic_url": "https://scontent-sea1-1.cdninstagram.com/v/t51.2885-19/66481559_2665515943675174_112270840254431232_n.jpg?stp=dst-jpg_s150x150&_nc_ht=scontent-sea1-1.cdninstagram.com&_nc_cat=110&_nc_ohc=MsKmV_GQVlQAX9Yd_sF&edm=ALB854YBAAAA&ccb=7-4&oh=00_AT9b9ApcE_0PBDq8HWCNBl9on8tcpGxnwdeN2i1N4vD0Qg&oe=62479C0F&_nc_sid=04cb80",
        "profile_pic_id": "2093322695105291639_12827775107",
        "is_verified": false,
        "follow_friction_type": 0,
        "growth_friction_info": {
            "has_active_interventions": false,
            "interventions": {}
        },
        "account_badges": [],
        "has_anonymous_profile_picture": false,
        "has_highlight_reels": false,
        "has_primary_country_in_feed": false,
        "has_primary_country_in_profile": false,
        "latest_reel_media": 0,
        "is_favorite": false
    },
    {
        "pk": 7841302232,
        "username": "wentsancheng",
        "full_name": "\u912d\u6587\u71e6",
        "is_private": false,
        "profile_pic_url": "https://scontent-sea1-1.cdninstagram.com/v/t51.2885-19/246898579_1217208982089694_910285058513152773_n.jpg?stp=dst-jpg_s150x150&_nc_ht=scontent-sea1-1.cdninstagram.com&_nc_cat=110&_nc_ohc=xjh6oiU6AKQAX-G9mSI&edm=ALB854YBAAAA&ccb=7-4&oh=00_AT9yEfKEQoESyCjYn8hx-XDeWold-AUMgiqtVs1Y3Pl0_A&oe=62480E4B&_nc_sid=04cb80",
        "profile_pic_id": "2689978941686838682_7841302232",
        "is_verified": true,
        "follow_friction_type": 0,
        "growth_friction_info": {
            "has_active_interventions": false,
            "interventions": {}
        },
        "account_badges": [],
        "has_anonymous_profile_picture": false,
        "has_highlight_reels": false,
        "has_primary_country_in_feed": false,
        "has_primary_country_in_profile": false,
        "latest_reel_media": 1648339137,
        "is_favorite": false
    },
    {
        "pk": 2014865078,
        "username": "karen_wanju_yu",
        "full_name": "\u4f59\u5b9b\u5982",
        "is_private": false,
        "profile_pic_url": "https://scontent-sea1-1.cdninstagram.com/v/t51.2885-19/118580654_204174401062448_1123394234297223265_n.jpg?stp=dst-jpg_s150x150&_nc_ht=scontent-sea1-1.cdninstagram.com&_nc_cat=108&_nc_ohc=rUYfIe4laioAX-zogs3&tn=5_nM7iDSx2Jrx7n9&edm=ALB854YBAAAA&ccb=7-4&oh=00_AT-EVHdmu0pJsctG5yQ6cicqX7iu_UR0nflmc1B3NjVpyw&oe=62471533&_nc_sid=04cb80",
        "profile_pic_id": "2385385380709676894_2014865078",
        "is_verified": true,
        "follow_friction_type": 0,
        "growth_friction_info": {
            "has_active_interventions": false,
            "interventions": {}
        },
        "account_badges": [],
        "has_anonymous_profile_picture": false,
        "has_highlight_reels": false,
        "has_primary_country_in_feed": false,
        "has_primary_country_in_profile": false,
        "latest_reel_media": 0,
        "is_favorite": false
    },
    {
        "pk": 7305022895,
        "username": "keelunging",
        "full_name": "\u8521\u9069\u61c9",
        "is_private": false,
        "profile_pic_url": "https://scontent-sea1-1.cdninstagram.com/v/t51.2885-19/46977978_1990737551005821_2927154361232523264_n.jpg?stp=dst-jpg_s150x150&_nc_ht=scontent-sea1-1.cdninstagram.com&_nc_cat=109&_nc_ohc=GRRD8_e-iAAAX8x86_o&edm=ALB854YBAAAA&ccb=7-4&oh=00_AT_AbGss-QZ0WXzcY4OKcD4ZdFsutFr0ucZdTdtXXz3zSg&oe=62464F2C&_nc_sid=04cb80",
        "profile_pic_id": "1937020826297672229_7305022895",
        "is_verified": true,
        "follow_friction_type": 0,
        "growth_friction_info": {
            "has_active_interventions": false,
            "interventions": {}
        },
        "account_badges": [],
        "has_anonymous_profile_picture": false,
        "has_highlight_reels": false,
        "has_primary_country_in_feed": false,
        "has_primary_country_in_profile": false,
        "latest_reel_media": 0,
        "is_favorite": false
    },
    {
        "pk": 8044111945,
        "username": "marcusfaberfdp",
        "full_name": "Marcus Faber",
        "is_private": false,
        "profile_pic_url": "https://scontent-sea1-1.cdninstagram.com/v/t51.2885-19/225063510_130343965851469_2948198553431925300_n.jpg?stp=dst-jpg_s150x150&_nc_ht=scontent-sea1-1.cdninstagram.com&_nc_cat=101&_nc_ohc=Gt6OZRxJHf8AX89oUBn&edm=ALB854YBAAAA&ccb=7-4&oh=00_AT-pbc2UwPtxdx512Ov8evcpis5vILsTAcg9dNA-SEADWg&oe=62471BD1&_nc_sid=04cb80",
        "profile_pic_id": "2627587206170260650_8044111945",
        "is_verified": true,
        "follow_friction_type": 0,
        "growth_friction_info": {
            "has_active_interventions": false,
            "interventions": {}
        },
        "account_badges": [],
        "has_anonymous_profile_picture": false,
        "has_highlight_reels": false,
        "has_primary_country_in_feed": false,
        "has_primary_country_in_profile": false,
        "latest_reel_media": 0,
        "is_favorite": false
    },
    {
        "pk": 7939513072,
        "username": "mofa_taiwan",
        "full_name": "\u5916\u4ea4\u90e8 MOFA Taiwan",
        "is_private": false,
        "profile_pic_url": "https://scontent-sea1-1.cdninstagram.com/v/t51.2885-19/119789012_374299387080516_6204101855008172203_n.jpg?stp=dst-jpg_s150x150&_nc_ht=scontent-sea1-1.cdninstagram.com&_nc_cat=100&_nc_ohc=o08sW4_Fws8AX_Wt76k&edm=ALB854YBAAAA&ccb=7-4&oh=00_AT9t_HOfzMDVLvwcAiXqrZkPIUetsUMMcktRBce3RTCqdw&oe=6246B9EE&_nc_sid=04cb80",
        "profile_pic_id": "2402949124282585350_7939513072",
        "is_verified": true,
        "follow_friction_type": 0,
        "growth_friction_info": {
            "has_active_interventions": false,
            "interventions": {}
        },
        "account_badges": [],
        "has_anonymous_profile_picture": false,
        "has_highlight_reels": false,
        "has_primary_country_in_feed": false,
        "has_primary_country_in_profile": false,
        "latest_reel_media": 0,
        "is_favorite": false
    },
    {
        "pk": 1826039894,
        "username": "dpp_taiwan",
        "full_name": "\u6c11\u9032\u9ee8DPP",
        "is_private": false,
        "profile_pic_url": "https://scontent-sea1-1.cdninstagram.com/v/t51.2885-19/15538503_140084319814925_3667826805777104896_a.jpg?stp=dst-jpg_s150x150&_nc_ht=scontent-sea1-1.cdninstagram.com&_nc_cat=105&_nc_ohc=g72tINPifSUAX_eSmEo&tn=5_nM7iDSx2Jrx7n9&edm=ALB854YBAAAA&ccb=7-4&oh=00_AT_VYKAagXQxiw2NX7c9o8PUvW654fM987RJCaaZ5s_7ng&oe=62473A71&_nc_sid=04cb80",
        "profile_pic_id": "1414182341119020232_1826039894",
        "is_verified": true,
        "follow_friction_type": 0,
        "growth_friction_info": {
            "has_active_interventions": false,
            "interventions": {}
        },
        "account_badges": [],
        "has_anonymous_profile_picture": false,
        "has_highlight_reels": false,
        "has_primary_country_in_feed": false,
        "has_primary_country_in_profile": false,
        "latest_reel_media": 0,
        "is_favorite": false
    },
    {
        "pk": 8247143916,
        "username": "muellerrosentritt",
        "full_name": "Frank Mu\u0308ller-Rosentritt MdB",
        "is_private": false,
        "profile_pic_url": "https://scontent-sea1-1.cdninstagram.com/v/t51.2885-19/43695420_255788071706895_8007943291913895936_n.jpg?stp=dst-jpg_s150x150&_nc_ht=scontent-sea1-1.cdninstagram.com&_nc_cat=103&_nc_ohc=-6c-JjF2qhkAX-iMQ9u&edm=ALB854YBAAAA&ccb=7-4&oh=00_AT9ay-GIPYftOAQxbdMlRqyhRdrtlxE0vCDMtefbwXue7A&oe=62475508&_nc_sid=04cb80",
        "profile_pic_id": "1897236052404319406_8247143916",
        "is_verified": true,
        "follow_friction_type": 0,
        "growth_friction_info": {
            "has_active_interventions": false,
            "interventions": {}
        },
        "account_badges": [],
        "has_anonymous_profile_picture": false,
        "has_highlight_reels": false,
        "has_primary_country_in_feed": false,
        "has_primary_country_in_profile": false,
        "latest_reel_media": 0,
        "is_favorite": false
    },
    {
        "pk": 8093748715,
        "username": "tsaimimi0416",
        "full_name": "\u8521\u5176\u660c",
        "is_private": false,
        "profile_pic_url": "https://scontent-sea1-1.cdninstagram.com/v/t51.2885-19/274149419_318032150349257_6594494843278994718_n.jpg?stp=dst-jpg_s150x150&_nc_ht=scontent-sea1-1.cdninstagram.com&_nc_cat=105&_nc_ohc=Q3zojTnJSVcAX9V8VkG&tn=5_nM7iDSx2Jrx7n9&edm=ALB854YBAAAA&ccb=7-4&oh=00_AT_nLqElGIEkGYt0MVkj2d1jtJeB-sED3cjeJe_V63Z9bA&oe=6246A36F&_nc_sid=04cb80",
        "profile_pic_id": "2776178945719315558_8093748715",
        "is_verified": true,
        "follow_friction_type": 0,
        "growth_friction_info": {
            "has_active_interventions": false,
            "interventions": {}
        },
        "account_badges": [],
        "has_anonymous_profile_picture": false,
        "has_highlight_reels": false,
        "has_primary_country_in_feed": false,
        "has_primary_country_in_profile": false,
        "latest_reel_media": 1648370383,
        "is_favorite": false
    },
    {
        "pk": 8352756688,
        "username": "ananpingtung",
        "full_name": "\u6f58\u5b5f\u5b89",
        "is_private": false,
        "profile_pic_url": "https://scontent-sea1-1.cdninstagram.com/v/t51.2885-19/271199112_993461991522081_4003180952527942331_n.jpg?stp=dst-jpg_s150x150&_nc_ht=scontent-sea1-1.cdninstagram.com&_nc_cat=1&_nc_ohc=30FCbvTpCUAAX8YL3J1&edm=ALB854YBAAAA&ccb=7-4&oh=00_AT80eEq07JXjZMa-Am9K9mG_cMx0TB9IC8LJO4pKJdBMtw&oe=62480EC1&_nc_sid=04cb80",
        "profile_pic_id": "2741963093222168381_8352756688",
        "is_verified": true,
        "follow_friction_type": 0,
        "growth_friction_info": {
            "has_active_interventions": false,
            "interventions": {}
        },
        "account_badges": [],
        "has_anonymous_profile_picture": false,
        "has_highlight_reels": false,
        "has_primary_country_in_feed": false,
        "has_primary_country_in_profile": false,
        "latest_reel_media": 1648372977,
        "is_favorite": false
    },
    {
        "pk": 10160923432,
        "username": "boching520",
        "full_name": "\u912d\u5bf6\u6e05",
        "is_private": false,
        "profile_pic_url": "https://scontent-sea1-1.cdninstagram.com/v/t51.2885-19/50934464_284964068856919_5452633528288149504_n.jpg?stp=dst-jpg_s150x150&_nc_ht=scontent-sea1-1.cdninstagram.com&_nc_cat=107&_nc_ohc=iHZH9vECJDEAX94YpHW&edm=ALB854YBAAAA&ccb=7-4&oh=00_AT-EbQARu9pOXhAncsgXEuvM3VoDnnz-ZQhQFMFzAMgWMg&oe=6246B8A8&_nc_sid=04cb80",
        "profile_pic_id": "1969787212253941458_10160923432",
        "is_verified": true,
        "follow_friction_type": 0,
        "growth_friction_info": {
            "has_active_interventions": false,
            "interventions": {}
        },
        "account_badges": [],
        "has_anonymous_profile_picture": false,
        "has_highlight_reels": false,
        "has_primary_country_in_feed": false,
        "has_primary_country_in_profile": false,
        "latest_reel_media": 0,
        "is_favorite": false
    },
    {
        "pk": 8131344954,
        "username": "bikhimhsiao",
        "full_name": "\u856d\u7f8e\u7434 Bikhim Hsiao",
        "is_private": false,
        "profile_pic_url": "https://scontent-sea1-1.cdninstagram.com/v/t51.2885-19/35998873_162153847989490_4340673397366194176_n.jpg?stp=dst-jpg_s150x150&_nc_ht=scontent-sea1-1.cdninstagram.com&_nc_cat=110&_nc_ohc=g5gH19UhoOkAX9-O_oZ&edm=ALB854YBAAAA&ccb=7-4&oh=00_AT9C1WnE6mCurOPVnfdr7EOiA9Ajh_wzO_ucgJwUhar7MQ&oe=6247B08B&_nc_sid=04cb80",
        "profile_pic_id": "1816576574881255998_8131344954",
        "is_verified": true,
        "follow_friction_type": 0,
        "growth_friction_info": {
            "has_active_interventions": false,
            "interventions": {}
        },
        "account_badges": [],
        "has_anonymous_profile_picture": false,
        "has_highlight_reels": false,
        "has_primary_country_in_feed": false,
        "has_primary_country_in_profile": false,
        "latest_reel_media": 0,
        "is_favorite": false
    },
    {
        "pk": 10579436143,
        "username": "weiche946",
        "full_name": "\u9ec3\u5049\u54f2",
        "is_private": false,
        "profile_pic_url": "https://scontent-sea1-1.cdninstagram.com/v/t51.2885-19/276175746_278879634398451_996518426573734148_n.jpg?stp=dst-jpg_s150x150&_nc_ht=scontent-sea1-1.cdninstagram.com&_nc_cat=103&_nc_ohc=aDSxuT7Auq4AX-mvcDm&tn=5_nM7iDSx2Jrx7n9&edm=ALB854YBAAAA&ccb=7-4&oh=00_AT8G8XrmvNIvyrGSL-eqKmrKJz0CcVm7BoPKCN5ujnACGw&oe=624803D6&_nc_sid=04cb80",
        "profile_pic_id": "2800872615192667027_10579436143",
        "is_verified": true,
        "follow_friction_type": 0,
        "growth_friction_info": {
            "has_active_interventions": false,
            "interventions": {}
        },
        "account_badges": [],
        "has_anonymous_profile_picture": false,
        "has_highlight_reels": false,
        "has_primary_country_in_feed": false,
        "has_primary_country_in_profile": false,
        "latest_reel_media": 1648348043,
        "is_favorite": false
    },
    {
        "pk": 8097577105,
        "username": "mainland_affairs_council",
        "full_name": "\u5927\u9678\u59d4\u54e1\u6703",
        "is_private": false,
        "profile_pic_url": "https://scontent-sea1-1.cdninstagram.com/v/t51.2885-19/277141640_819729045649952_7280908179733656831_n.jpg?stp=dst-jpg_s150x150&_nc_ht=scontent-sea1-1.cdninstagram.com&_nc_cat=108&_nc_ohc=4X7wnKO7SMIAX9YAWmH&edm=ALB854YBAAAA&ccb=7-4&oh=00_AT_TaUu-BrNGtwg6hCaf1Pl0SwP-7LsOzeylzbTed-NYhA&oe=6247B614&_nc_sid=04cb80",
        "profile_pic_id": "2799292632485838279_8097577105",
        "is_verified": true,
        "follow_friction_type": 0,
        "growth_friction_info": {
            "has_active_interventions": false,
            "interventions": {}
        },
        "account_badges": [],
        "has_anonymous_profile_picture": false,
        "has_highlight_reels": false,
        "has_primary_country_in_feed": false,
        "has_primary_country_in_profile": false,
        "latest_reel_media": 0,
        "is_favorite": false
    },
    {
        "pk": 8098963520,
        "username": "tienlinchao_sky",
        "full_name": "\u8d99\u5929\u9e9f",
        "is_private": false,
        "profile_pic_url": "https://scontent-sea1-1.cdninstagram.com/v/t51.2885-19/122396519_195331382031380_4875415360861333861_n.jpg?stp=dst-jpg_s150x150&_nc_ht=scontent-sea1-1.cdninstagram.com&_nc_cat=108&_nc_ohc=AF9OMZYdmzoAX8YQ9iA&edm=ALB854YBAAAA&ccb=7-4&oh=00_AT_vzAxcXhWVE6A-2Kwv78FU0vbpjafv9uHzxpgfeIAF8Q&oe=62479412&_nc_sid=04cb80",
        "profile_pic_id": "2427447997397534908_8098963520",
        "is_verified": true,
        "follow_friction_type": 0,
        "growth_friction_info": {
            "has_active_interventions": false,
            "interventions": {}
        },
        "account_badges": [],
        "has_anonymous_profile_picture": false,
        "has_highlight_reels": false,
        "has_primary_country_in_feed": false,
        "has_primary_country_in_profile": false,
        "latest_reel_media": 1648338122,
        "is_favorite": false
    },
    {
        "pk": 4770970465,
        "username": "lin_chihchien",
        "full_name": "\u6797\u667a\u5805",
        "is_private": false,
        "profile_pic_url": "https://scontent-sea1-1.cdninstagram.com/v/t51.2885-19/17075921_757629631053615_1530628947321028608_a.jpg?stp=dst-jpg_s150x150&_nc_ht=scontent-sea1-1.cdninstagram.com&_nc_cat=103&_nc_ohc=gxC-pUo5QuMAX-TZlsl&edm=ALB854YBAAAA&ccb=7-4&oh=00_AT_1gmr5N5FOLshvaGyWcY1mIvMBJkfpWWE_rgttizUNjA&oe=62477433&_nc_sid=04cb80",
        "profile_pic_id": "1464464433022588419_4770970465",
        "is_verified": true,
        "follow_friction_type": 0,
        "growth_friction_info": {
            "has_active_interventions": false,
            "interventions": {}
        },
        "account_badges": [],
        "has_anonymous_profile_picture": false,
        "has_highlight_reels": false,
        "has_primary_country_in_feed": false,
        "has_primary_country_in_profile": false,
        "latest_reel_media": 1648376237,
        "is_favorite": false
    },
    {
        "pk": 1598435783,
        "username": "souichi_lai",
        "full_name": "\u8cf4\u7e3d\u4e00",
        "is_private": false,
        "profile_pic_url": "https://scontent-sea1-1.cdninstagram.com/v/t51.2885-19/40465556_307709000031990_4347029304719179776_n.jpg?stp=dst-jpg_s150x150&_nc_ht=scontent-sea1-1.cdninstagram.com&_nc_cat=106&_nc_ohc=duTerKUI-rEAX9dfdXg&tn=5_nM7iDSx2Jrx7n9&edm=ALB854YBAAAA&ccb=7-4&oh=00_AT8Kr_kmuOkYXLgS1TONki5sAKmy18ZXbjR_KoyNiAqztg&oe=6246B19C&_nc_sid=04cb80",
        "profile_pic_id": "1863791400036113296_1598435783",
        "is_verified": false,
        "follow_friction_type": 0,
        "growth_friction_info": {
            "has_active_interventions": false,
            "interventions": {}
        },
        "account_badges": [],
        "has_anonymous_profile_picture": false,
        "has_highlight_reels": false,
        "has_primary_country_in_feed": false,
        "has_primary_country_in_profile": false,
        "latest_reel_media": 0,
        "is_favorite": false
    },
    {
        "pk": 13147487667,
        "username": "leer0105",
        "full_name": "\u9ad8\u96c4\u5c0f\u91d1\u525b\u9cf3\u5c71\u7acb\u59d4\u8a31\u667a\u5091",
        "is_private": false,
        "profile_pic_url": "https://scontent-sea1-1.cdninstagram.com/v/t51.2885-19/71133519_502008317314418_1677781330110185472_n.jpg?stp=dst-jpg_s150x150&_nc_ht=scontent-sea1-1.cdninstagram.com&_nc_cat=102&_nc_ohc=3_iWv0bu1IYAX-0HFEp&edm=ALB854YBAAAA&ccb=7-4&oh=00_AT_uzVKApgXYH7yJkfSRh4b5o2VjItk4QAH4_fsgCGcfwg&oe=62481D4D&_nc_sid=04cb80",
        "profile_pic_id": "2156604305847540007_13147487667",
        "is_verified": true,
        "follow_friction_type": 0,
        "growth_friction_info": {
            "has_active_interventions": false,
            "interventions": {}
        },
        "account_badges": [],
        "has_anonymous_profile_picture": false,
        "has_highlight_reels": false,
        "has_primary_country_in_feed": false,
        "has_primary_country_in_profile": false,
        "latest_reel_media": 0,
        "is_favorite": false
    },
    {
        "pk": 5912907058,
        "username": "chunyi_lee_",
        "full_name": "\u674e\u4fca\u4fcb",
        "is_private": false,
        "profile_pic_url": "https://scontent-sea1-1.cdninstagram.com/v/t51.2885-19/21041674_227960537731708_6318704608260653056_a.jpg?stp=dst-jpg_s150x150&_nc_ht=scontent-sea1-1.cdninstagram.com&_nc_cat=104&_nc_ohc=Fc6IQ52vGwwAX-9Ixm3&edm=ALB854YBAAAA&ccb=7-4&oh=00_AT_kpAIpkh7p4XG6r8saNrA0ZrDwHQZV8EkpVuyLoZfZEw&oe=62466497&_nc_sid=04cb80",
        "profile_pic_id": "1586148937156597773_5912907058",
        "is_verified": false,
        "follow_friction_type": 0,
        "growth_friction_info": {
            "has_active_interventions": false,
            "interventions": {}
        },
        "account_badges": [],
        "has_anonymous_profile_picture": false,
        "has_highlight_reels": false,
        "has_primary_country_in_feed": false,
        "has_primary_country_in_profile": false,
        "latest_reel_media": 0,
        "is_favorite": false
    },
    {
        "pk": 3312557821,
        "username": "retina_anchorman",
        "full_name": "\u8996\u7db2\u819cRetina",
        "is_private": false,
        "profile_pic_url": "https://scontent-sea1-1.cdninstagram.com/v/t51.2885-19/138433672_165234364997956_6759525232936800750_n.jpg?stp=dst-jpg_s150x150&_nc_ht=scontent-sea1-1.cdninstagram.com&_nc_cat=1&_nc_ohc=IW3GhzNGI-YAX_xBbz3&edm=ALB854YBAAAA&ccb=7-4&oh=00_AT9IvC8CyLVn1JfLocGgV8N2HrTnQt64GF4R_hOj5mNXrQ&oe=62467E64&_nc_sid=04cb80",
        "profile_pic_id": "2486931730518389985_3312557821",
        "is_verified": true,
        "follow_friction_type": 0,
        "growth_friction_info": {
            "has_active_interventions": false,
            "interventions": {}
        },
        "account_badges": [],
        "has_anonymous_profile_picture": false,
        "has_highlight_reels": false,
        "has_primary_country_in_feed": false,
        "has_primary_country_in_profile": false,
        "latest_reel_media": 1648376045,
        "is_favorite": false
    },
    {
        "pk": 16751617844,
        "username": "lin_chingyi_physician",
        "full_name": "\u6797\u975c\u5100",
        "is_private": false,
        "profile_pic_url": "https://scontent-sea1-1.cdninstagram.com/v/t51.2885-19/226366807_1015237759285579_7001845635875462284_n.jpg?stp=dst-jpg_s150x150&_nc_ht=scontent-sea1-1.cdninstagram.com&_nc_cat=107&_nc_ohc=6Bet7k0XE-cAX8ATfyo&tn=5_nM7iDSx2Jrx7n9&edm=ALB854YBAAAA&ccb=7-4&oh=00_AT9tMv1Y3MPcJIcJrSdQjtEGe4_rqU_ZMATN5i9L-5Ym2w&oe=6247B289&_nc_sid=04cb80",
        "profile_pic_id": "2629253056512187989_16751617844",
        "is_verified": false,
        "follow_friction_type": 0,
        "growth_friction_info": {
            "has_active_interventions": false,
            "interventions": {}
        },
        "account_badges": [],
        "has_anonymous_profile_picture": false,
        "has_highlight_reels": false,
        "has_primary_country_in_feed": false,
        "has_primary_country_in_profile": false,
        "latest_reel_media": 0,
        "is_favorite": false
    },
    {
        "pk": 17653605072,
        "username": "nong.taiwan",
        "full_name": "\u5433\u6021\u8fb2",
        "is_private": false,
        "profile_pic_url": "https://scontent-sea1-1.cdninstagram.com/v/t51.2885-19/91025144_213579913073079_8354421524907687936_n.jpg?stp=dst-jpg_s150x150&_nc_ht=scontent-sea1-1.cdninstagram.com&_nc_cat=103&_nc_ohc=T_i_PdxW1YwAX9X21Le&tn=5_nM7iDSx2Jrx7n9&edm=ALB854YBAAAA&ccb=7-4&oh=00_AT_RqlkUjWTNGcAf5hZni2TB42-1rMDx19337lFJ2MF10w&oe=62466CC0&_nc_sid=04cb80",
        "profile_pic_id": "2275636602502069441_17653605072",
        "is_verified": true,
        "follow_friction_type": 0,
        "growth_friction_info": {
            "has_active_interventions": false,
            "interventions": {}
        },
        "account_badges": [],
        "has_anonymous_profile_picture": false,
        "has_highlight_reels": false,
        "has_primary_country_in_feed": false,
        "has_primary_country_in_profile": false,
        "latest_reel_media": 0,
        "is_favorite": false
    },
    {
        "pk": 6738899121,
        "username": "shinzoabe",
        "full_name": "\u5b89\u500d \u664b\u4e09",
        "is_private": false,
        "profile_pic_url": "https://scontent-sea1-1.cdninstagram.com/v/t51.2885-19/174119314_733106097355536_1787393451790459133_n.jpg?stp=dst-jpg_s150x150&_nc_ht=scontent-sea1-1.cdninstagram.com&_nc_cat=100&_nc_ohc=k9QjhHnPqwIAX-_GPLX&tn=5_nM7iDSx2Jrx7n9&edm=ALB854YBAAAA&ccb=7-4&oh=00_AT_U06k1kb_nW9UzM0hLg5L7CQAX5q_kC7IfW4Sc2V73YQ&oe=62470530&_nc_sid=04cb80",
        "profile_pic_id": "2558737215494524278_6738899121",
        "is_verified": true,
        "follow_friction_type": 0,
        "growth_friction_info": {
            "has_active_interventions": false,
            "interventions": {}
        },
        "account_badges": [],
        "has_anonymous_profile_picture": false,
        "has_highlight_reels": false,
        "has_primary_country_in_feed": false,
        "has_primary_country_in_profile": false,
        "latest_reel_media": 0,
        "is_favorite": false
    },
    {
        "pk": 3954316686,
        "username": "eballgogogo",
        "full_name": "\u8607\u8c9e\u660c",
        "is_private": false,
        "profile_pic_url": "https://scontent-sea1-1.cdninstagram.com/v/t51.2885-19/36161337_1805279969563697_7576649311774048256_n.jpg?stp=dst-jpg_s150x150&_nc_ht=scontent-sea1-1.cdninstagram.com&_nc_cat=105&_nc_ohc=B6Jp2PKSgrMAX8yJ3nt&edm=ALB854YBAAAA&ccb=7-4&oh=00_AT-4z1tGQFzP2wOkD9ZvDHw4hwuZjqCA_6t_Q6oquSf5QA&oe=624768F7&_nc_sid=04cb80",
        "profile_pic_id": "1343108968028967677_3954316686",
        "is_verified": true,
        "follow_friction_type": 0,
        "growth_friction_info": {
            "has_active_interventions": false,
            "interventions": {}
        },
        "account_badges": [],
        "has_anonymous_profile_picture": false,
        "has_highlight_reels": false,
        "has_primary_country_in_feed": false,
        "has_primary_country_in_profile": false,
        "latest_reel_media": 0,
        "is_favorite": false
    },
    {
        "pk": 3312289659,
        "username": "chuangjuihsiung",
        "full_name": "\u838a\u745e\u96c4",
        "is_private": false,
        "profile_pic_url": "https://scontent-sea1-1.cdninstagram.com/v/t51.2885-19/13298235_244869782551977_450080754_a.jpg?stp=dst-jpg_s150x150&_nc_ht=scontent-sea1-1.cdninstagram.com&_nc_cat=109&_nc_ohc=Uyji2FGzV_kAX9CeCKm&edm=ALB854YBAAAA&ccb=7-4&oh=00_AT--7kFKzAlmMqM2164uOu2sZn51d5yvOk03KqPRPHvYrQ&oe=62475F39&_nc_sid=04cb80",
        "profile_pic_id": "1267526863266828622_3312289659",
        "is_verified": true,
        "follow_friction_type": 0,
        "growth_friction_info": {
            "has_active_interventions": false,
            "interventions": {}
        },
        "account_badges": [],
        "has_anonymous_profile_picture": false,
        "has_highlight_reels": false,
        "has_primary_country_in_feed": false,
        "has_primary_country_in_profile": false,
        "latest_reel_media": 0,
        "is_favorite": false
    },
    {
        "pk": 4031717883,
        "username": "chenchimai",
        "full_name": "\u9673\u5176\u9081",
        "is_private": false,
        "profile_pic_url": "https://scontent-sea1-1.cdninstagram.com/v/t51.2885-19/60692226_847024992321075_7028489524913111040_n.jpg?stp=dst-jpg_s150x150&_nc_ht=scontent-sea1-1.cdninstagram.com&_nc_cat=103&_nc_ohc=X7K1_OvVuoEAX-rFzqT&edm=ALB854YBAAAA&ccb=7-4&oh=00_AT9Kd6BU1CemgX1byLX9W7ll0RpwyS-eMrxwIHCw0Uejeg&oe=6247AA3B&_nc_sid=04cb80",
        "profile_pic_id": "2056832333303844266_4031717883",
        "is_verified": true,
        "follow_friction_type": 0,
        "growth_friction_info": {
            "has_active_interventions": false,
            "interventions": {}
        },
        "account_badges": [],
        "has_anonymous_profile_picture": false,
        "has_highlight_reels": false,
        "has_primary_country_in_feed": false,
        "has_primary_country_in_profile": false,
        "latest_reel_media": 1648370333,
        "is_favorite": false
    },
    {
        "pk": 18245381950,
        "username": "chiayiawen",
        "full_name": "\u9673\u660e\u6587",
        "is_private": false,
        "profile_pic_url": "https://scontent-sea1-1.cdninstagram.com/v/t51.2885-19/68929076_412206612732500_3163035064640471040_n.jpg?stp=dst-jpg_s150x150&_nc_ht=scontent-sea1-1.cdninstagram.com&_nc_cat=108&_nc_ohc=2WUKOhUTqosAX8YKtR5&tn=5_nM7iDSx2Jrx7n9&edm=ALB854YBAAAA&ccb=7-4&oh=00_AT_dWWGGgST4QKO_28UfAT4TOqnyulHQy_lwKqs7IDF8wQ&oe=62481BE8&_nc_sid=04cb80",
        "profile_pic_id": "2111643488025203704_18245381950",
        "is_verified": false,
        "follow_friction_type": 0,
        "growth_friction_info": {
            "has_active_interventions": false,
            "interventions": {}
        },
        "account_badges": [],
        "has_anonymous_profile_picture": false,
        "has_highlight_reels": false,
        "has_primary_country_in_feed": false,
        "has_primary_country_in_profile": false,
        "latest_reel_media": 0,
        "is_favorite": false
    },
    {
        "pk": 5572646881,
        "username": "rocmid",
        "full_name": "\u570b\u9632\u90e8\u767c\u8a00\u4eba\u5b98\u65b9IG",
        "is_private": false,
        "profile_pic_url": "https://scontent-sea1-1.cdninstagram.com/v/t51.2885-19/41959637_534878716973143_3142650647342481408_n.jpg?stp=dst-jpg_s150x150&_nc_ht=scontent-sea1-1.cdninstagram.com&_nc_cat=107&_nc_ohc=ftvw_YS7XVEAX9RdcIR&edm=ALB854YBAAAA&ccb=7-4&oh=00_AT8f6ucSYeMAkZfylkPHy46eTtUFEhmfiWW5Zl9e_9nTag&oe=6247FF50&_nc_sid=04cb80",
        "profile_pic_id": "1881994691449236960_5572646881",
        "is_verified": true,
        "follow_friction_type": 0,
        "growth_friction_info": {
            "has_active_interventions": false,
            "interventions": {}
        },
        "account_badges": [],
        "has_anonymous_profile_picture": false,
        "has_highlight_reels": false,
        "has_primary_country_in_feed": false,
        "has_primary_country_in_profile": false,
        "latest_reel_media": 1648301734,
        "is_favorite": false
    },
    {
        "pk": 5438142439,
        "username": "dragonforpeople",
        "full_name": "\u6797\u4f73\u9f8d",
        "is_private": false,
        "profile_pic_url": "https://scontent-sea1-1.cdninstagram.com/v/t51.2885-19/234370167_856620774977105_8134912506010810352_n.jpg?stp=dst-jpg_s150x150&_nc_ht=scontent-sea1-1.cdninstagram.com&_nc_cat=105&_nc_ohc=EAPEDLuYYcUAX_yTjz_&tn=5_nM7iDSx2Jrx7n9&edm=ALB854YBAAAA&ccb=7-4&oh=00_AT8QPrXSGTX3WUhu-Gk1F7Wm3sw2Wabs_SWYNBHeotiFkw&oe=624821E6&_nc_sid=04cb80",
        "profile_pic_id": "2636239576934790236_5438142439",
        "is_verified": true,
        "follow_friction_type": 0,
        "growth_friction_info": {
            "has_active_interventions": false,
            "interventions": {}
        },
        "account_badges": [],
        "has_anonymous_profile_picture": false,
        "has_highlight_reels": false,
        "has_primary_country_in_feed": false,
        "has_primary_country_in_profile": false,
        "latest_reel_media": 0,
        "is_favorite": false
    },
    {
        "pk": 10812956050,
        "username": "ho_art_501",
        "full_name": "\u4f55\u5fd7\u5049",
        "is_private": false,
        "profile_pic_url": "https://scontent-sea1-1.cdninstagram.com/v/t51.2885-19/51273550_377107353103111_7569837884484616192_n.jpg?stp=dst-jpg_s150x150&_nc_ht=scontent-sea1-1.cdninstagram.com&_nc_cat=107&_nc_ohc=CMJmc6ucJf4AX_veWyF&edm=ALB854YBAAAA&ccb=7-4&oh=00_AT8zVjCEbiAYcIuSODuxhUOFtRAKfqCrPN4gUTkrRDscdQ&oe=6246F61F&_nc_sid=04cb80",
        "profile_pic_id": "1968354441933496602_10812956050",
        "is_verified": true,
        "follow_friction_type": 0,
        "growth_friction_info": {
            "has_active_interventions": false,
            "interventions": {}
        },
        "account_badges": [],
        "has_anonymous_profile_picture": false,
        "has_highlight_reels": false,
        "has_primary_country_in_feed": false,
        "has_primary_country_in_profile": false,
        "latest_reel_media": 0,
        "is_favorite": false
    },
    {
        "pk": 4104957399,
        "username": "cheng_yunpeng",
        "full_name": "\u912d\u904b\u9d6c",
        "is_private": false,
        "profile_pic_url": "https://scontent-sea1-1.cdninstagram.com/v/t51.2885-19/130798819_3522163711238485_4188905785229821853_n.jpg?stp=dst-jpg_s150x150&_nc_ht=scontent-sea1-1.cdninstagram.com&_nc_cat=101&_nc_ohc=akJASPxhdGMAX_bTWSS&tn=5_nM7iDSx2Jrx7n9&edm=ALB854YBAAAA&ccb=7-4&oh=00_AT8ilzc7Tar-7fa0zwSLyz3ZlNAntEBUMbHD3tlxuZG7wg&oe=6246CB27&_nc_sid=04cb80",
        "profile_pic_id": "2460014835011439489_4104957399",
        "is_verified": false,
        "follow_friction_type": 0,
        "growth_friction_info": {
            "has_active_interventions": false,
            "interventions": {}
        },
        "account_badges": [],
        "has_anonymous_profile_picture": false,
        "has_highlight_reels": false,
        "has_primary_country_in_feed": false,
        "has_primary_country_in_profile": false,
        "latest_reel_media": 0,
        "is_favorite": false
    },
    {
        "pk": 5466329293,
        "username": "shua0522",
        "full_name": "\u8a31\u6dd1\u83ef",
        "is_private": false,
        "profile_pic_url": "https://scontent-sea1-1.cdninstagram.com/v/t51.2885-19/244978171_599116167893745_2172513021440765057_n.jpg?stp=dst-jpg_s150x150&_nc_ht=scontent-sea1-1.cdninstagram.com&_nc_cat=109&_nc_ohc=xR38njJXDZoAX_NumGd&edm=ALB854YBAAAA&ccb=7-4&oh=00_AT_I7istawH07vw7Mx_V8KPNtti4E8SVK0iwt-53XdVwsw&oe=6246F61F&_nc_sid=04cb80",
        "profile_pic_id": "2680666951805892579_5466329293",
        "is_verified": true,
        "follow_friction_type": 0,
        "growth_friction_info": {
            "has_active_interventions": false,
            "interventions": {}
        },
        "account_badges": [],
        "has_anonymous_profile_picture": false,
        "has_highlight_reels": false,
        "has_primary_country_in_feed": false,
        "has_primary_country_in_profile": false,
        "latest_reel_media": 0,
        "is_favorite": false
    },
    {
        "pk": 7332781420,
        "username": "chen_tingfei",
        "full_name": "\u9673\u4ead\u5983 a.k.a\u53f0\u5357\u81ea\u5df1\u7684\u5973\u5152",
        "is_private": false,
        "profile_pic_url": "https://scontent-sea1-1.cdninstagram.com/v/t51.2885-19/73138137_545770919584171_1155372303140257792_n.jpg?stp=dst-jpg_s150x150&_nc_ht=scontent-sea1-1.cdninstagram.com&_nc_cat=107&_nc_ohc=lU2ZmBBBicIAX-mnzVi&edm=ALB854YBAAAA&ccb=7-4&oh=00_AT97GDof3je-_aznh1FwjLlYgIv-a0E7nW1V3iGCNd7N6g&oe=62475896&_nc_sid=04cb80",
        "profile_pic_id": "2159605347461954732_7332781420",
        "is_verified": true,
        "follow_friction_type": 0,
        "growth_friction_info": {
            "has_active_interventions": false,
            "interventions": {}
        },
        "account_badges": [],
        "has_anonymous_profile_picture": false,
        "has_highlight_reels": false,
        "has_primary_country_in_feed": false,
        "has_primary_country_in_profile": false,
        "latest_reel_media": 0,
        "is_favorite": false
    },
    {
        "pk": 2246441819,
        "username": "kuanmom",
        "full_name": "\u7ba1\u78a7\u73b2",
        "is_private": false,
        "profile_pic_url": "https://scontent-sea1-1.cdninstagram.com/v/t51.2885-19/16908341_604774876383807_4439709995977670656_a.jpg?stp=dst-jpg_s150x150&_nc_ht=scontent-sea1-1.cdninstagram.com&_nc_cat=103&_nc_ohc=6oooVhr0POoAX_JdU9v&edm=ALB854YBAAAA&ccb=7-4&oh=00_AT-mYtthZ5_CIrL79qajZ52oCB1XXg_SxzkL8T8AExdDhA&oe=62482B2E&_nc_sid=04cb80",
        "profile_pic_id": "1464638435218020761_2246441819",
        "is_verified": false,
        "follow_friction_type": 0,
        "growth_friction_info": {
            "has_active_interventions": false,
            "interventions": {}
        },
        "account_badges": [],
        "has_anonymous_profile_picture": false,
        "has_highlight_reels": false,
        "has_primary_country_in_feed": false,
        "has_primary_country_in_profile": false,
        "latest_reel_media": 0,
        "is_favorite": false
    },
    {
        "pk": 2808225919,
        "username": "chiming0224",
        "full_name": "\u5433\u742a\u9298",
        "is_private": false,
        "profile_pic_url": "https://scontent-sea1-1.cdninstagram.com/v/t51.2885-19/72998849_1014021102264391_9140607514549682176_n.jpg?stp=dst-jpg_s150x150&_nc_ht=scontent-sea1-1.cdninstagram.com&_nc_cat=107&_nc_ohc=UcTkCeehoqEAX8RX11D&edm=ALB854YBAAAA&ccb=7-4&oh=00_AT-IwxaW523XU3zFU1KAztIP75ElsyAPELBDGr3eMnd5yg&oe=624665CA&_nc_sid=04cb80",
        "profile_pic_id": "2181149176016779790_2808225919",
        "is_verified": true,
        "follow_friction_type": 0,
        "growth_friction_info": {
            "has_active_interventions": false,
            "interventions": {}
        },
        "account_badges": [],
        "has_anonymous_profile_picture": false,
        "has_highlight_reels": false,
        "has_primary_country_in_feed": false,
        "has_primary_country_in_profile": false,
        "latest_reel_media": 0,
        "is_favorite": false
    },
    {
        "pk": 9450656547,
        "username": "wuyuchindpp",
        "full_name": "\u5433\u7389\u7434",
        "is_private": false,
        "profile_pic_url": "https://scontent-sea1-1.cdninstagram.com/v/t51.2885-19/59954439_880387648965290_8954093551789015040_n.jpg?stp=dst-jpg_s150x150&_nc_ht=scontent-sea1-1.cdninstagram.com&_nc_cat=102&_nc_ohc=k9Axlp08VRkAX_QMx6X&edm=ALB854YBAAAA&ccb=7-4&oh=00_AT-GwNGEv4HuXay91zFuYD52XeNEKYnJi-LZR6qN5s2aIw&oe=62477AFB&_nc_sid=04cb80",
        "profile_pic_id": "2042730332249535204_9450656547",
        "is_verified": false,
        "follow_friction_type": 0,
        "growth_friction_info": {
            "has_active_interventions": false,
            "interventions": {}
        },
        "account_badges": [],
        "has_anonymous_profile_picture": false,
        "has_highlight_reels": false,
        "has_primary_country_in_feed": false,
        "has_primary_country_in_profile": false,
        "latest_reel_media": 0,
        "is_favorite": false
    },
    {
        "pk": 13386148510,
        "username": "su_zhenqing",
        "full_name": "\u8607\u9707\u6e05",
        "is_private": false,
        "profile_pic_url": "https://scontent-sea1-1.cdninstagram.com/v/t51.2885-19/59695158_454062198470533_788555011998089216_n.jpg?stp=dst-jpg_s150x150&_nc_ht=scontent-sea1-1.cdninstagram.com&_nc_cat=101&_nc_ohc=INZbLr_FHLoAX_r9wqx&edm=ALB854YBAAAA&ccb=7-4&oh=00_AT8cE2YJnsa2lXWRoIXb1ySMVliv8No6XN-L6hk9aLRq0w&oe=62469DB5&_nc_sid=04cb80",
        "profile_pic_id": "2041965590690117638_13386148510",
        "is_verified": false,
        "follow_friction_type": 0,
        "growth_friction_info": {
            "has_active_interventions": false,
            "interventions": {}
        },
        "account_badges": [],
        "has_anonymous_profile_picture": false,
        "has_highlight_reels": false,
        "has_primary_country_in_feed": false,
        "has_primary_country_in_profile": false,
        "latest_reel_media": 0,
        "is_favorite": false
    }
]