[
    {
        "pk": 8192019677,
        "username": "vegetable.han",
        "full_name": "\u97d3\u570b\u745c",
        "is_private": false,
        "profile_pic_url": "https://scontent-tpe1-1.cdninstagram.com/v/t51.2885-19/160017337_305108921037609_2858483372389905778_n.jpg?stp=dst-jpg_s150x150&_nc_ht=scontent-tpe1-1.cdninstagram.com&_nc_cat=109&_nc_ohc=y_8JXRX2-N8AX8NdzU2&tn=ZLYK010uleidVms5&edm=ALB854YBAAAA&ccb=7-4&oh=00_AT_6EJRLeVkh7xoKdGLKA6HOWNzKmPMGx0a6jPPI5e8JQQ&oe=6249577E&_nc_sid=04cb80",
        "profile_pic_id": "2529916792078218278_8192019677",
        "is_verified": true,
        "follow_friction_type": 0,
        "growth_friction_info": {
            "has_active_interventions": false,
            "interventions": {}
        },
        "account_badges": [],
        "has_anonymous_profile_picture": false,
        "has_highlight_reels": false,
        "has_primary_country_in_feed": false,
        "has_primary_country_in_profile": false,
        "latest_reel_media": 0,
        "is_favorite": false
    },
    {
        "pk": 8608439417,
        "username": "sancheng624",
        "full_name": "\u570b\u5bb6\u5de5\u7a0b\u5e2b\uff1a\u5f35\u5584\u653f",
        "is_private": false,
        "profile_pic_url": "https://scontent-tpe1-1.cdninstagram.com/v/t51.2885-19/42154272_867476546975029_2330115634634948608_n.jpg?stp=dst-jpg_s150x150&_nc_ht=scontent-tpe1-1.cdninstagram.com&_nc_cat=101&_nc_ohc=A9ql-dZonPcAX85c3C-&edm=ALB854YBAAAA&ccb=7-4&oh=00_AT9LZwyGOeZaLlq2ShL2vsUkoyRM2YfBjC0v-4pa-ytCaQ&oe=62491BC8&_nc_sid=04cb80",
        "profile_pic_id": "1872353870670189163_8608439417",
        "is_verified": false,
        "follow_friction_type": 0,
        "growth_friction_info": {
            "has_active_interventions": false,
            "interventions": {}
        },
        "account_badges": [],
        "has_anonymous_profile_picture": false,
        "has_highlight_reels": false,
        "has_primary_country_in_feed": false,
        "has_primary_country_in_profile": false,
        "latest_reel_media": 0,
        "is_favorite": false
    }
]